ical2orgpy/__init__.py
ical2orgpy-0.5.dist-info/AUTHORS
ical2orgpy-0.5.dist-info/LICENSE.txt
ical2orgpy-0.5.dist-info/METADATA
ical2orgpy-0.5.dist-info/WHEEL
ical2orgpy-0.5.dist-info/entry_points.txt
ical2orgpy-0.5.dist-info/top_level.txt
ical2orgpy-0.5.dist-info/RECORD
