Metadata-Version: 2.1
Name: ical2orgpy
Version: 0.5
Summary: Convert ICAL/ICS files into Emacs org-mode format.
Home-page: https://github.com/ical2org-py/ical2org.py
Author: Aitor Soroa
Author-email: a.soroa@gmail.com
License: GPLv3
Keywords: calendar,ical,org,emacs
Platform: UNKNOWN
Classifier: Development Status :: 4 - Beta
Classifier: Environment :: Console
Classifier: Operating System :: OS Independent
Classifier: Programming Language :: Python
Classifier: Programming Language :: Python :: 3.5
Classifier: Programming Language :: Python :: 3.6
Classifier: Programming Language :: Python :: 3.7
Classifier: Programming Language :: Python :: 3.8
Classifier: Programming Language :: Python :: 3.9
Classifier: Programming Language :: Python :: 3.10
Classifier: Programming Language :: Python :: 3.11
License-File: LICENSE.txt
License-File: AUTHORS
Requires-Dist: click
Requires-Dist: future
Requires-Dist: icalendar
Requires-Dist: pytz
Requires-Dist: tzlocal
Requires-Dist: recurring-ical-events (>=2.0.1)
